tortoise_pydantic_bridge/__init__.py
tortoise_pydantic_bridge/core.py
tortoise_pydantic_bridge/crud.py
tortoise_pydantic_bridge/generic.py
tortoise_pydantic_bridge/mixins.py
tortoise_pydantic_bridge-0.1.1.dist-info/METADATA
tortoise_pydantic_bridge-0.1.1.dist-info/WHEEL
tortoise_pydantic_bridge-0.1.1.dist-info/RECORD
