Metadata-Version: 2.4
Name: tortoise-pydantic-bridge
Version: 0.1.1
Summary: Мост между Tortoise ORM и Pydantic для конвертации моделей
Author: pasha_danilevich
Author-email: danilevitch.pasha@yandex.ru
Requires-Python: >=3.9,<3.13
Classifier: Programming Language :: Python :: 3
Classifier: Programming Language :: Python :: 3.9
Classifier: Programming Language :: Python :: 3.10
Classifier: Programming Language :: Python :: 3.11
Classifier: Programming Language :: Python :: 3.12
Requires-Dist: pydantic (>=2.0.0)
Requires-Dist: tortoise-orm (>=0.19.0)
